slate/__init__.py
slate/api.py
slate/exceptions.py
slate/slate.py
slate/utils.py
slate/backtest/__init__.py
slate/backtest/backtest.py
slate/cli/__init__.py
slate/cli/api.py
slate/cli/deploy.py
slate/cli/login.py
slate/cli/ui.py
slate/integrations/__init__.py
slate/integrations/backtesting_py.py
slate/integrations/bt_py.py
slate/integrations/common.py
slate/integrations/jesse_ai.py
slate/live/__init__.py
slate/live/live.py
slate/model/__init__.py
slate/model/model.py
blankly_slate-1.10.6b0.dist-info/LICENSE
blankly_slate-1.10.6b0.dist-info/METADATA
blankly_slate-1.10.6b0.dist-info/WHEEL
blankly_slate-1.10.6b0.dist-info/entry_points.txt
blankly_slate-1.10.6b0.dist-info/top_level.txt
blankly_slate-1.10.6b0.dist-info/RECORD
