Metadata-Version: 2.1
Name: blankly-slate
Version: 1.10.6b0
Summary: View, manage and share your model from any codebase with slate
Home-page: https://blankly.finance
Author: blankly
License: mit
Classifier: Development Status :: 4 - Beta
Classifier: Intended Audience :: Developers
Classifier: Intended Audience :: Financial and Insurance Industry
Classifier: License :: OSI Approved :: MIT License
Classifier: Programming Language :: Python :: 3.7
Classifier: Programming Language :: Python :: 3.8
Classifier: Programming Language :: Python :: 3.9
Classifier: Programming Language :: Python :: 3.10
License-File: LICENSE
Requires-Dist: questionary (>=1.10.0)
Requires-Dist: yaspin (>=2.1.0)
Requires-Dist: requests
Requires-Dist: pandas
Requires-Dist: numpy
